django_vehiclefitment/__init__.py
django_vehiclefitment/fitment_data_storage.py
django_vehiclefitment/models.py
django_vehiclefitment/migrations/0001_initial.py
django_vehiclefitment/migrations/__init__.py
django_vehiclefitment-1.0.1.dist-info/DESCRIPTION.rst
django_vehiclefitment-1.0.1.dist-info/LICENSE.txt
django_vehiclefitment-1.0.1.dist-info/METADATA
django_vehiclefitment-1.0.1.dist-info/RECORD
django_vehiclefitment-1.0.1.dist-info/WHEEL
django_vehiclefitment-1.0.1.dist-info/metadata.json
django_vehiclefitment-1.0.1.dist-info/top_level.txt
