Metadata-Version: 2.0
Name: django-vehiclefitment
Version: 1.0.1
Summary: Vehicle fitment for django autoparts models
Home-page: https://github.com/MChiciak/django-vehiclefitment
Author: Michael Chiciak
Author-email: mchicia1@gmail.com
License: MIT license
Platform: unix
Platform: linux
Platform: osx
Platform: win32
Requires-Python: >=3.0
Requires-Dist: django
Requires-Dist: django-datatools
